simple_slurm/__about__.py
simple_slurm/__init__.py
simple_slurm/arguments.txt
simple_slurm/arguments_help.txt
simple_slurm/cli.py
simple_slurm/core.py
simple_slurm/filename_patterns.txt
simple_slurm/output_env_vars.txt
simple_slurm/scancel.py
simple_slurm/squeue.py
simple_slurm-0.3.6.dist-info/licenses/LICENSE
test/__init__.py
test/test_cli.py
test/test_core.py
simple_slurm-0.3.6.dist-info/METADATA
simple_slurm-0.3.6.dist-info/WHEEL
simple_slurm-0.3.6.dist-info/entry_points.txt
simple_slurm-0.3.6.dist-info/top_level.txt
simple_slurm-0.3.6.dist-info/RECORD
