Metadata-Version: 2.4
Name: simple_slurm
Version: 0.3.6
Summary: A simple Python wrapper for Slurm with flexibility in mind.
Home-page: https://github.com/amq92/simple_slurm
Author: Arturo Mendoza
License: GNU Affero General Public License v3
Classifier: Programming Language :: Python :: 3
Classifier: License :: OSI Approved :: GNU Affero General Public License v3
Classifier: Operating System :: OS Independent
Classifier: Development Status :: 5 - Production/Stable
Requires-Python: >=3.6
License-File: LICENSE
Dynamic: author
Dynamic: classifier
Dynamic: description
Dynamic: description-content-type
Dynamic: home-page
Dynamic: license
Dynamic: license-file
Dynamic: requires-python
Dynamic: summary
